alibabacloud_gpdb20160503/__init__.py
alibabacloud_gpdb20160503/client.py
alibabacloud_gpdb20160503/models/__init__.py
alibabacloud_gpdb20160503/models/_add_ainode_request.py
alibabacloud_gpdb20160503/models/_add_ainode_response.py
alibabacloud_gpdb20160503/models/_add_ainode_response_body.py
alibabacloud_gpdb20160503/models/_allocate_instance_public_connection_request.py
alibabacloud_gpdb20160503/models/_allocate_instance_public_connection_response.py
alibabacloud_gpdb20160503/models/_allocate_instance_public_connection_response_body.py
alibabacloud_gpdb20160503/models/_bind_dbresource_group_with_role_request.py
alibabacloud_gpdb20160503/models/_bind_dbresource_group_with_role_response.py
alibabacloud_gpdb20160503/models/_bind_dbresource_group_with_role_response_body.py
alibabacloud_gpdb20160503/models/_bind_dbresource_group_with_role_shrink_request.py
alibabacloud_gpdb20160503/models/_cancel_create_index_job_request.py
alibabacloud_gpdb20160503/models/_cancel_create_index_job_response.py
alibabacloud_gpdb20160503/models/_cancel_create_index_job_response_body.py
alibabacloud_gpdb20160503/models/_cancel_upload_document_job_request.py
alibabacloud_gpdb20160503/models/_cancel_upload_document_job_response.py
alibabacloud_gpdb20160503/models/_cancel_upload_document_job_response_body.py
alibabacloud_gpdb20160503/models/_cancel_upsert_collection_data_job_request.py
alibabacloud_gpdb20160503/models/_cancel_upsert_collection_data_job_response.py
alibabacloud_gpdb20160503/models/_cancel_upsert_collection_data_job_response_body.py
alibabacloud_gpdb20160503/models/_chat_with_knowledge_base_request.py
alibabacloud_gpdb20160503/models/_chat_with_knowledge_base_response.py
alibabacloud_gpdb20160503/models/_chat_with_knowledge_base_response_body.py
alibabacloud_gpdb20160503/models/_chat_with_knowledge_base_shrink_request.py
alibabacloud_gpdb20160503/models/_chat_with_knowledge_base_stream_request.py
alibabacloud_gpdb20160503/models/_chat_with_knowledge_base_stream_response.py
alibabacloud_gpdb20160503-5.0.1.dist-info/LICENSE
alibabacloud_gpdb20160503-5.0.1.dist-info/METADATA
alibabacloud_gpdb20160503-5.0.1.dist-info/WHEEL
alibabacloud_gpdb20160503-5.0.1.dist-info/top_level.txt
alibabacloud_gpdb20160503-5.0.1.dist-info/RECORD
